PcapAnalyzeHelper/__init__.py
PcapAnalyzeHelper/features.py
PcapAnalyzeHelper/general_stat.py
PcapAnalyzeHelper/pcap_parse.py
PcapAnalyzeHelper/pcap_summarize.py
PcapAnalyzeHelper-0.1.4.dist-info/METADATA
PcapAnalyzeHelper-0.1.4.dist-info/WHEEL
PcapAnalyzeHelper-0.1.4.dist-info/top_level.txt
PcapAnalyzeHelper-0.1.4.dist-info/RECORD
