Metadata-Version: 2.1
Name: PcapAnalyzeHelper
Version: 0.1.4
Summary: A python package for quick analysis on pcap file
Home-page: UNKNOWN
Author: wenjwang
Author-email: wenjade91@gmail.com
License: MIT
Platform: UNKNOWN
Requires-Python: >=3.6
Requires-Dist: numpy
Requires-Dist: pandas
Requires-Dist: scapy
Requires-Dist: matplotlib
Requires-Dist: seaborn
